{
  "updated": "2026-05-29T09:11:22+08:00",
  "market": {
    "taiex": 43636.44,
    "taiex_chg": -620.36,
    "taiex_chg_pct": -1.4,
    "foreign_net_m": 0.0,
    "dealer_net_m": 0.0,
    "trust_net_m": -6206.04,
    "three_inst_total_m": -6206.04,
    "pressure": "Neutral",
    "foreign_net_m_prev": 0.0,
    "dealer_net_m_prev": 0.0,
    "trust_net_m_prev": -6206.04
  },
  "portfolio": [
    {
      "code": "2330",
      "ticker": "2330",
      "name_en": "TSMC",
      "name_zh": "台積電",
      "sector": "SEMI",
      "bucket": "portfolio",
      "close": 2295.0,
      "chg": -5.0,
      "chg_pct": -0.22,
      "volume": 42313277.0,
      "ma5": 2286.0,
      "ma20": 2252.25,
      "ma60": 2044.67,
      "vol_ratio": 1.24,
      "high_52w": 2360.0,
      "low_52w": 946.0,
      "pct_from_52w_high": -2.75,
      "trend": "BULL",
      "foreign_net": -5003302.0,
      "trust_net": 0.0,
      "dealer_net": 13000.0,
      "inst_net": -4990302.0,
      "foreign_3d": -3270995.0,
      "foreign_5d": -6973963.0,
      "trust_3d": 0.0,
      "trust_5d": 0.0,
      "foreign_streak": -2,
      "trust_streak": 0,
      "l1_score": -0.125,
      "signal_score": 2,
      "signal_label": "Bull"
    },
    {
      "code": "2317",
      "ticker": "2317",
      "name_en": "Hon Hai",
      "name_zh": "鴻海",
      "sector": "ELEC",
      "bucket": "portfolio",
      "close": 263.0,
      "chg": -1.0,
      "chg_pct": -0.38,
      "volume": 73792269.0,
      "ma5": 259.4,
      "ma20": 248.3,
      "ma60": 222.04,
      "vol_ratio": 0.95,
      "high_52w": 269.5,
      "low_52w": 151.0,
      "pct_from_52w_high": -2.41,
      "trend": "BULL",
      "foreign_net": -1914792.0,
      "trust_net": 0.0,
      "dealer_net": 395000.0,
      "inst_net": -1519792.0,
      "foreign_3d": 30567307.0,
      "foreign_5d": 91899106.0,
      "trust_3d": 0.0,
      "trust_5d": 0.0,
      "foreign_streak": -1,
      "trust_streak": 0,
      "l1_score": 0.25,
      "signal_score": 3,
      "signal_label": "Strong Bull"
    }
  ],
  "watchlist": [
    {
      "code": "2454",
      "ticker": "2454",
      "name_en": "MediaTek",
      "name_zh": "聯發科",
      "sector": "SEMI",
      "bucket": "watchlist",
      "close": 4410.0,
      "chg": -230.0,
      "chg_pct": -4.96,
      "volume": 16433052.0,
      "ma5": 4284.0,
      "ma20": 3580.5,
      "ma60": 2392.58,
      "vol_ratio": 1.03,
      "high_52w": 4690.0,
      "low_52w": 1130.0,
      "pct_from_52w_high": -5.97,
      "trend": "BULL",
      "foreign_net": 162052.0,
      "trust_net": 0.0,
      "dealer_net": 81000.0,
      "inst_net": 243052.0,
      "foreign_3d": 3159887.0,
      "foreign_5d": 3352676.0,
      "trust_3d": 0.0,
      "trust_5d": 0.0,
      "foreign_streak": 3,
      "trust_streak": 0,
      "l1_score": 0.25,
      "signal_score": 3,
      "signal_label": "Strong Bull"
    },
    {
      "code": "2382",
      "ticker": "2382",
      "name_en": "Quanta",
      "name_zh": "廣達",
      "sector": "ELEC",
      "bucket": "watchlist",
      "close": 308.5,
      "chg": -3.5,
      "chg_pct": -1.12,
      "volume": 43210473.0,
      "ma5": 313.9,
      "ma20": 320.23,
      "ma60": 307.13,
      "vol_ratio": 1.0,
      "high_52w": 352.5,
      "low_52w": 252.5,
      "pct_from_52w_high": -12.48,
      "trend": "MIXED-",
      "foreign_net": -566000.0,
      "trust_net": 0.0,
      "dealer_net": 14000.0,
      "inst_net": -552000.0,
      "foreign_3d": -39664103.0,
      "foreign_5d": -75495261.0,
      "trust_3d": 0.0,
      "trust_5d": 0.0,
      "foreign_streak": -5,
      "trust_streak": 0,
      "l1_score": -0.099,
      "signal_score": -1,
      "signal_label": "Bear"
    },
    {
      "code": "2303",
      "ticker": "2303",
      "name_en": "UMC",
      "name_zh": "聯電",
      "sector": "SEMI",
      "bucket": "watchlist",
      "close": 142.0,
      "chg": -1.5,
      "chg_pct": -1.05,
      "volume": 418286433.0,
      "ma5": 131.0,
      "ma20": 106.98,
      "ma60": 77.77,
      "vol_ratio": 1.36,
      "high_52w": 151.0,
      "low_52w": 40.1,
      "pct_from_52w_high": -5.96,
      "trend": "BULL",
      "foreign_net": -8342000.0,
      "trust_net": 0.0,
      "dealer_net": 835000.0,
      "inst_net": -7507000.0,
      "foreign_3d": 13247154.0,
      "foreign_5d": 133637530.0,
      "trust_3d": 0.0,
      "trust_5d": 0.0,
      "foreign_streak": -1,
      "trust_streak": 0,
      "l1_score": 0.25,
      "signal_score": 3,
      "signal_label": "Strong Bull"
    },
    {
      "code": "6505",
      "ticker": "6505",
      "name_en": "Formosa Petro",
      "name_zh": "台塑化",
      "sector": "PETRO",
      "bucket": "watchlist",
      "close": 49.9,
      "chg": -0.2,
      "chg_pct": -0.4,
      "volume": 9178702.0,
      "ma5": 49.96,
      "ma20": 52.22,
      "ma60": 54.71,
      "vol_ratio": 1.04,
      "high_52w": 68.2,
      "low_52w": 34.9,
      "pct_from_52w_high": -26.83,
      "trend": "BEAR",
      "foreign_net": 746000.0,
      "trust_net": 0.0,
      "dealer_net": 0.0,
      "inst_net": 746000.0,
      "foreign_3d": 3510976.0,
      "foreign_5d": -2798862.0,
      "trust_3d": 0.0,
      "trust_5d": 0.0,
      "foreign_streak": 1,
      "trust_streak": 0,
      "l1_score": -0.15,
      "signal_score": -3,
      "signal_label": "Strong Bear"
    },
    {
      "code": "2002",
      "ticker": "2002",
      "name_en": "China Steel",
      "name_zh": "中鋼",
      "sector": "STEEL",
      "bucket": "watchlist",
      "close": 18.85,
      "chg": -0.25,
      "chg_pct": -1.31,
      "volume": 85146738.0,
      "ma5": 19.11,
      "ma20": 18.63,
      "ma60": 19.19,
      "vol_ratio": 0.6,
      "high_52w": 21.6,
      "low_52w": 17.6,
      "pct_from_52w_high": -12.73,
      "trend": "MIXED+",
      "foreign_net": -1238140.0,
      "trust_net": 0.0,
      "dealer_net": 70000.0,
      "inst_net": -1168140.0,
      "foreign_3d": -42240757.0,
      "foreign_5d": -41782615.0,
      "trust_3d": 0.0,
      "trust_5d": 0.0,
      "foreign_streak": -4,
      "trust_streak": 0,
      "l1_score": -0.114,
      "signal_score": 1,
      "signal_label": "Bull"
    },
    {
      "code": "1301",
      "ticker": "1301",
      "name_en": "Formosa Plastics",
      "name_zh": "台塑",
      "sector": "PETRO",
      "bucket": "watchlist",
      "close": 45.05,
      "chg": -0.4,
      "chg_pct": -0.88,
      "volume": 16825189.0,
      "ma5": 45.06,
      "ma20": 47.31,
      "ma60": 48.2,
      "vol_ratio": 0.89,
      "high_52w": 56.3,
      "low_52w": 32.95,
      "pct_from_52w_high": -19.98,
      "trend": "BEAR",
      "foreign_net": 156925.0,
      "trust_net": 0.0,
      "dealer_net": 8000.0,
      "inst_net": 164925.0,
      "foreign_3d": 1874648.0,
      "foreign_5d": -8451009.0,
      "trust_3d": 0.0,
      "trust_5d": 0.0,
      "foreign_streak": 1,
      "trust_streak": 0,
      "l1_score": -0.144,
      "signal_score": -2,
      "signal_label": "Bear"
    },
    {
      "code": "2881",
      "ticker": "2881",
      "name_en": "Fubon FHC",
      "name_zh": "富邦金",
      "sector": "FIN",
      "bucket": "watchlist",
      "close": 110.0,
      "chg": 0.0,
      "chg_pct": 0.0,
      "volume": 83541343.0,
      "ma5": 103.26,
      "ma20": 96.62,
      "ma60": 91.11,
      "vol_ratio": 1.13,
      "high_52w": 112.0,
      "low_52w": 79.2,
      "pct_from_52w_high": -1.79,
      "trend": "BULL",
      "foreign_net": 1879000.0,
      "trust_net": 0.0,
      "dealer_net": 236000.0,
      "inst_net": 2115000.0,
      "foreign_3d": 81741836.0,
      "foreign_5d": 101340971.0,
      "trust_3d": 0.0,
      "trust_5d": 0.0,
      "foreign_streak": 4,
      "trust_streak": 0,
      "l1_score": 0.25,
      "signal_score": 3,
      "signal_label": "Strong Bull"
    },
    {
      "code": "2882",
      "ticker": "2882",
      "name_en": "Cathay FHC",
      "name_zh": "國泰金",
      "sector": "FIN",
      "bucket": "watchlist",
      "close": 84.8,
      "chg": -0.6,
      "chg_pct": -0.7,
      "volume": 61980458.0,
      "ma5": 82.9,
      "ma20": 79.03,
      "ma60": 75.0,
      "vol_ratio": 1.12,
      "high_52w": 86.4,
      "low_52w": 58.8,
      "pct_from_52w_high": -1.85,
      "trend": "BULL",
      "foreign_net": -1882000.0,
      "trust_net": 0.0,
      "dealer_net": 70000.0,
      "inst_net": -1812000.0,
      "foreign_3d": 38937319.0,
      "foreign_5d": 83753851.0,
      "trust_3d": 0.0,
      "trust_5d": 0.0,
      "foreign_streak": -1,
      "trust_streak": 0,
      "l1_score": 0.18,
      "signal_score": 3,
      "signal_label": "Strong Bull"
    },
    {
      "code": "0050",
      "ticker": "0050",
      "name_en": "Taiwan 50 ETF",
      "name_zh": "元大台灣50",
      "sector": "ETF",
      "bucket": "watchlist",
      "close": 100.5,
      "chg": -2.05,
      "chg_pct": -2.0,
      "volume": 152915695.0,
      "ma5": 100.25,
      "ma20": 96.42,
      "ma60": 85.17,
      "vol_ratio": 1.43,
      "high_52w": 188.9,
      "low_52w": 46.28,
      "pct_from_52w_high": -46.8,
      "trend": "BULL",
      "foreign_net": -1261000.0,
      "trust_net": 0.0,
      "dealer_net": 107000.0,
      "inst_net": -1154000.0,
      "foreign_3d": -37747381.0,
      "foreign_5d": -32893798.0,
      "trust_3d": 0.0,
      "trust_5d": 0.0,
      "foreign_streak": -2,
      "trust_streak": 0,
      "l1_score": -0.05,
      "signal_score": 2,
      "signal_label": "Bull"
    },
    {
      "code": "0056",
      "ticker": "0056",
      "name_en": "Hi-Div ETF",
      "name_zh": "元大高股息",
      "sector": "ETF",
      "bucket": "watchlist",
      "close": 48.83,
      "chg": -0.81,
      "chg_pct": -1.63,
      "volume": 62678749.0,
      "ma5": 48.3,
      "ma20": 45.22,
      "ma60": 41.25,
      "vol_ratio": 1.06,
      "high_52w": 50.1,
      "low_52w": 33.45,
      "pct_from_52w_high": -2.53,
      "trend": "BULL",
      "foreign_net": 0.0,
      "trust_net": 0.0,
      "dealer_net": 359000.0,
      "inst_net": 359000.0,
      "foreign_3d": 16472139.0,
      "foreign_5d": 46285019.0,
      "trust_3d": 0.0,
      "trust_5d": 0.0,
      "foreign_streak": 0,
      "trust_streak": 0,
      "l1_score": 0.25,
      "signal_score": 3,
      "signal_label": "Strong Bull"
    }
  ],
  "analysis": {
    "updated": "2026-05-28T08:40:00+08:00",
    "summary": "0528 盤前 — 外資狂買 381 億，台股衝破 44,000 大關，成交量創歷史新天量 1.6 兆元。\n\n加權指數前日高低差達千點，終場收 44,256（+731），開高走低留長上影線，但仍沿 5MA 多頭排列。外資單日淨買 381 億護盤，內資投信高檔反向調節 43 億，籌碼分歧需關注。\n\n櫃買指數持續創歷史新高，收 440 點，成交額 4,000 億元。\n\n今日關鍵觀察：大盤能否縮量守住 44,000，若 K 線站穩中值，高檔換手成功。切忌追高偏離均線的 IP 概念股，聚焦法人持續加碼的業績股。\n\n【強勢】晶圓代工（聯電漲停）、證券期貨（致和證/康和證/宏遠證漲停）、固態電容（凱美/立隆電漲停，鉅邦 +5%）\n【弱勢】IP/ASIC 概念（世芯-KY -3%、創意 -3.5%、智原 -2.6%）、玻纖布（富喬/建榮 -4%，德宏 -6%）\n\n美股：三大指數週三同創歷史新高（費城半導體除外，-1%），WTI 原油暴跌逾 5% 至 88.68 美元，中東局勢降溫。今日聚焦 PCE 通膨數據（Fed 偏好指標），觀察新主席 Kevin Warsh 政策方向。",
    "callouts": [
      {
        "ticker": "2303",
        "label": "聯電 — ADR 飆漲 15% 引領漲停",
        "flag": "bull",
        "note": "受美股 ADR 暴漲激勵，台股帶量攻漲停，成為大盤最強撐盤要角。成熟製程需求回溫，外資持續買超。",
        "action": "未持有 — 漲停後若回測 MA5 守穩可考慮小量試單；已有倉位可持有至回測 MA20 再評估減碼"
      },
      {
        "ticker": "2337",
        "label": "旺宏 — Q1 轉虧為盈，下半年調漲價格",
        "flag": "bull",
        "note": "Q1 EPS 0.9 元，毛利率衝上 40.8%，終結連續十季虧損。NAND/eMMC 供不應求訂單直達下半年，NOR Flash 及 SLC NAND 下半年持續調漲實質報價。股價尚未創高，持續關注。",
        "action": "未持有 — 下半年調漲報價為實質催化劑，可在量縮回檔至月線附近建立核心倉位"
      },
      {
        "ticker": "6770",
        "label": "力積電 — 美光擴產反成利多",
        "flag": "bull",
        "note": "美光重返 DDR4 市場擴產，力積電因持有美光 1y 奈米 DRAM 製程授權，在成熟產能緊縮中逆勢受惠。外資籌碼持續站買方，盤中一度大漲 7.49%。",
        "action": "未持有 — 外資連買訊號明確；若持有應持股觀察，止損設月線跌破收盤"
      },
      {
        "ticker": "2317",
        "label": "鴻海 — NVIDIA AI 平台三大通吃",
        "flag": "bull",
        "note": "獲得 Vera Rubin NVL72 液冷、HGX Rubin NVL8、MGX 模組化伺服器三大次世代 AI 基礎建設訂單，法人最新報告稱鴻海在 NVIDIA 新平台展現「全面通吃」霸主地位，獲利能見度極高。",
        "action": "持有中 — 訂單能見度高，無需操作；若短線漲多可於前高區輕減 10-15% 鎖定部分獲利"
      },
      {
        "ticker": "IP概念",
        "label": "IP/ASIC 概念股 — 連續兩日重挫",
        "flag": "bear",
        "note": "世芯-KY -3% 跌破 20MA 轉弱，創意 -3.5%，智原 -2.6%。缺乏短期營收實績、僅靠高 P/E 支撐，高檔震盪時極易成為法人換股的流動性提款機。",
        "action": "未直接持有 — 若組合有 IP/ASIC 相關部位（如世芯），跌破月線應考慮減碼或停損出場"
      }
    ],
    "sources": [
      "投資早報 2026-05-28",
      "TWSE API",
      "三大法人 BFI82U"
    ]
  }
}